latexman/__init__.py
latexman/functions.py
latexman-0.5.dist-info/LICENSE
latexman-0.5.dist-info/METADATA
latexman-0.5.dist-info/WHEEL
latexman-0.5.dist-info/top_level.txt
latexman-0.5.dist-info/RECORD
