Metadata-Version: 2.1
Name: latexman
Version: 0.5
Summary: latex code manipulation
Home-page: https://github.com/imahdimir/latexman
Author: Mahdi Mir
Author-email: imahdimir@gmail.com
Project-URL: Bug Tracker, https://github.com/imahdimir/latexman/issues
Classifier: Programming Language :: Python :: 3
Classifier: License :: OSI Approved :: MIT License
Classifier: Operating System :: OS Independent
Requires-Python: >=3.6
License-File: LICENSE
